{"friendly_id": "his-house", "UUID": "1ed3db65-a4dd-4113-9fb8-548507de302f", "Title": "His House", "Year": "2020", "Runtime": "93 mins", "Rating": "3.5", "Watches": "106K", "Lists": "24K", "Likes": "24K", "Director": "Remi Weekes", "Top 250 Position": "N/A", "Description": "After making a harrowing escape from war-torn South Sudan, a young refugee couple struggle to adjust to their new life in a small English town that has an unspeakable evil lurking beneath the surface.", "Poster": "https://a.ltrbxd.com/resized/film-poster/5/0/3/8/8/9/503889-his-house-0-230-0-345-crop.jpg?v=c034af4a42"}