{"friendly_id": "when-marnie-was-there", "UUID": "79180545-43df-4c03-9998-30d702c79708", "Title": "When Marnie Was There", "Year": "2014", "Runtime": "103 mins", "Rating": "3.8", "Watches": "115K", "Lists": "32K", "Likes": "34K", "Director": "Hiromasa Yonebayashi", "Top 250 Position": "N/A", "Description": "Upon being sent to live with relatives in the countryside due to an illness, an emotionally distant adolescent girl becomes obsessed with an abandoned mansion and infatuated with a girl who lives there - a girl who may or may not be real.", "Poster": "https://a.ltrbxd.com/resized/film-poster/1/7/0/0/6/2/170062-when-marnie-was-there-0-230-0-345-crop.jpg?v=7e34859d4e"}