{"friendly_id": "scream-2", "UUID": "19433f80-3362-4a12-a711-d3878fd38122", "Title": "Scream 2", "Year": "1997", "Runtime": "120 mins", "Rating": "3.3", "Watches": "282K", "Lists": "52K", "Likes": "56K", "Director": "Wes Craven", "Top 250 Position": "N/A", "Description": "Two years after the terrifying events that occurred in Woodsboro, Sidney is now attending Windsor College in Cincinnati, and Gale Weathers\u2019 best selling book on Sidney\u2019s life has now been made into a major motion picture. When two college students are killed in a theatre while watching the new film \u2018Stab\u2019, Sidney knows deep down that history is repeating itself.", "Poster": "https://a.ltrbxd.com/resized/sm/upload/ju/sr/4r/t3/c5AyWNWooMGkJXlqLwmPQCjUwHt-0-230-0-345-crop.jpg?v=b19f368866"}