{"friendly_id": "the-machinist", "UUID": "6f5d35ab-4c1b-438c-a426-6ef4de0e07d1", "Title": "The Machinist", "Year": "2004", "Runtime": "101 mins", "Rating": "3.7", "Watches": "230K", "Lists": "25K", "Likes": "47K", "Director": "Brad Anderson", "Top 250 Position": "N/A", "Description": "The Machinist is the story of Trevor Reznik, a lathe-operator who is dying of insomnia. In a machine shop, occupational hazards are bad enough under normal circumstances; yet for Trevor the risks are compounded by fatigue. Trevor has lost the ability to sleep. This is no ordinary insomnia\u2026", "Poster": "https://a.ltrbxd.com/resized/film-poster/4/9/2/5/4/49254-the-machinist-0-230-0-345-crop.jpg?v=71a9922e95"}