{"friendly_id": "home-alone-2-lost-in-new-york", "UUID": "aa8f951e-3bf9-46a6-8cbb-b6af5fb76642", "Title": "Home Alone 2: Lost in New York", "Year": "1992", "Runtime": "120 mins", "Rating": "3.3", "Watches": "578K", "Lists": "37K", "Likes": "88K", "Director": "Chris Columbus", "Top 250 Position": "N/A", "Description": "Instead of flying to Florida with his folks, Kevin ends up alone in New York, where he gets a hotel room with his dad\u2019s credit card\u2014despite problems from a clerk and meddling bellboy. But when Kevin runs into his old nemeses, the Wet Bandits, he\u2019s determined to foil their plans to rob a toy store on Christmas eve.", "Poster": "https://a.ltrbxd.com/resized/sm/upload/i5/04/e8/7t/home%20alone%202-0-230-0-345-crop.jpg?v=03abfa6a99"}