{"friendly_id": "solaris", "UUID": "ae0c9374-2385-46ea-9f8a-82c6154ab366", "Title": "Solaris", "Year": "1972", "Runtime": "167 mins", "Rating": "4.2", "Watches": "138K", "Lists": "59K", "Likes": "43K", "Director": "Andrei Tarkovsky", "Top 250 Position": "222", "Description": "A psychologist is sent to a space station orbiting a planet called Solaris to investigate the death of a doctor and the mental problems of cosmonauts on the station. He soon discovers that the water on the planet is a type of brain which brings out repressed memories and obsessions.", "Poster": "https://a.ltrbxd.com/resized/film-poster/5/1/5/2/8/51528-solaris-0-230-0-345-crop.jpg?v=18b2bcf9ce"}