{"friendly_id": "click", "UUID": "c29ce534-e071-4e35-b4eb-c4677634a07e", "Title": "Click", "Year": "2006", "Runtime": "107 mins", "Rating": "2.7", "Watches": "412K", "Lists": "19K", "Likes": "40K", "Director": "Frank Coraci", "Top 250 Position": "N/A", "Description": "A harried workaholic, Michael Newman doesn\u2019t have time for his wife and children, not if he\u2019s to impress his ungrateful boss and earn a well-deserved promotion. So when he meets Morty, a loopy sales clerk, he gets the answer to his prayers: a magical remote that allows him to bypass life\u2019s little distractions with increasingly hysterical results.", "Poster": "https://a.ltrbxd.com/resized/film-poster/4/7/2/5/5/47255-click-0-230-0-345-crop.jpg?v=21dfe24b64"}