{"friendly_id": "apollo-13", "UUID": "59555950-2f1d-4639-adf3-af3426f90f2b", "Title": "Apollo 13", "Year": "1995", "Runtime": "140 mins", "Rating": "3.7", "Watches": "211K", "Lists": "28K", "Likes": "37K", "Director": "Ron Howard", "Top 250 Position": "N/A", "Description": "The true story of technical troubles that scuttle the Apollo 13 lunar mission in 1971, risking the lives of astronaut Jim Lovell and his crew, with the failed journey turning into a thrilling saga of heroism. Drifting more than 200,000 miles from Earth, the astronauts work furiously with the ground crew to avert tragedy.", "Poster": "https://a.ltrbxd.com/resized/film-poster/5/1/5/5/1/51551-apollo-13-0-230-0-345-crop.jpg?v=256e0eeb8f"}