{"friendly_id": "salo-or-the-120-days-of-sodom", "UUID": "68387557-10a9-482b-98de-2fb6a7a92798", "Title": "Sal\u00f2, or the 120 Days of Sodom", "Year": "1975", "Runtime": "117 mins", "Rating": "3.2", "Watches": "114K", "Lists": "35K", "Likes": "19K", "Director": "Pier Paolo Pasolini", "Top 250 Position": "N/A", "Description": "Four corrupted fascist libertines round up 9 teenage boys and girls and subject them to 120 days of sadistic physical, mental and sexual torture.", "Poster": "https://a.ltrbxd.com/resized/film-poster/4/8/8/6/5/48865-salo-or-the-120-days-of-sodom-0-230-0-345-crop.jpg?v=d44ef57732"}