{"friendly_id": "bridget-joness-diary", "UUID": "5c16ff9a-458f-4d75-9054-21eae54ca5d5", "Title": "Bridget Jones\u2019s Diary", "Year": "2001", "Runtime": "97 mins", "Rating": "3.4", "Watches": "299K", "Lists": "37K", "Likes": "51K", "Director": "Sharon Maguire", "Top 250 Position": "N/A", "Description": "A chaotic Bridget Jones meets a snobbish lawyer, and he soon enters her world of imperfections.", "Poster": "https://a.ltrbxd.com/resized/sm/upload/0u/jf/ve/sc/ydsXlFK0fmOphAIjqsmf5U6j1LU-0-230-0-345-crop.jpg?v=d771ae3fb2"}