{"friendly_id": "the-perks-of-being-a-wallflower", "UUID": "122f569e-9dc9-4f18-a53e-f1021f538598", "Title": "The Perks of Being a Wallflower", "Year": "2012", "Runtime": "103 mins", "Rating": "3.9", "Watches": "1M", "Lists": "123K", "Likes": "354K", "Director": "Stephen Chbosky", "Top 250 Position": "N/A", "Description": "Pittsburgh, Pennsylvania, 1991. High school freshman Charlie is a wallflower, always watching life from the sidelines, until two senior students, Sam and her stepbrother Patrick, become his mentors, helping him discover the joys of friendship, music and love\u2026", "Poster": "https://a.ltrbxd.com/resized/sm/upload/zz/o0/mz/sv/fyYncUQh5gUTvxmQ4bigm2DVCv7-0-230-0-345-crop.jpg?v=1188bcf4af"}